LICENSE
xjtlu/__init__.py
xjtlu/auth/__init__.py
xjtlu/utils/__init__.py
xjtlu-0.1.0.dist-info/LICENSE
xjtlu-0.1.0.dist-info/METADATA
xjtlu-0.1.0.dist-info/WHEEL
xjtlu-0.1.0.dist-info/RECORD
