Metadata-Version: 2.1
Name: xjtlu
Version: 0.1.0
Summary: This is how to get all the network resources of XJTLU
Home-page: https://github.com/AprilNEA/XJTLU
License: GPL-3
Keywords: XJTLU
Author: AprilNEA
Author-email: github@sku.moe
Requires-Python: >=3.9,<4
Classifier: License :: Other/Proprietary License
Classifier: Programming Language :: Python :: 3
Classifier: Programming Language :: Python :: 3.9
Classifier: Programming Language :: Python :: 3.10
Classifier: Programming Language :: Python :: 3.11
Requires-Dist: aiohttp (>=3.8.6,<4.0.0)
Requires-Dist: beautifulsoup4 (>=4.12.2,<5.0.0)
Requires-Dist: fake-useragent (>=1.3.0,<2.0.0)
Project-URL: Repository, https://github.com/AprilNEA/XJTLU
